[
{
  "topicName": "Sound",
  "front": "What is analogue sound?",
  "back": "<pre>A continuous sound wave that changes smoothly over time.\n\nAnalogue (continuous):\n\n    /‾\\    /‾\\    /‾\\\n   /   \\  /   \\  /   \\\n___/     \\/     \\/     \\___\n</pre>"
}
  {
    "topicName": "Sound",
    "front": "What is digital sound?",
    "back": "Sound stored as binary numbers."
  },
  {
    "topicName": "Sound",
    "front": "What is sampling?",
    "back": "Measuring sound at regular time intervals."
  },
  {
    "topicName": "Sound",
    "front": "What is sampling rate?",
    "back": "The number of samples taken per second (Hz)."
  },
  {
    "topicName": "Sound",
    "front": "What is sample resolution?",
    "back": "The number of bits used per sample."
  },
  {
    "topicName": "Sound",
    "front": "What is another name for sample resolution?",
    "back": "Bit depth."
  },
  {
    "topicName": "Sound",
    "front": "What happens to file size when sampling rate increases?",
    "back": "File size increases."
  },
  {
    "topicName": "Sound",
    "front": "What happens to file size when sample resolution increases?",
    "back": "File size increases."
  }
]
