[
  {
    "topicName": "Maintainable Programs",
    "mcq": {
      "question": "What is a maintainable program?",
      "correct": "Easy to read, test and modify",
      "wrong": [
        "Fast to run on any device",
        "Shorter than other programs",
        "Written using only loops"
      ]
    }
  },
  {
    "topicName": "Maintainable Programs",
    "mcq": {
      "question": "Why are maintainable programs important?",
      "correct": "They are easier to update",
      "wrong": [
        "They always use less memory",
        "They avoid all syntax errors",
        "They run faster automatically"
      ]
    }
  },
  {
    "topicName": "Maintainable Programs",
    "mcq": {
      "question": "Which of these is a meaningful identifier?",
      "correct": "totalScore",
      "wrong": [
        "x",
        "a1",
        "temp"
      ]
    }
  },
  {
    "topicName": "Maintainable Programs",
    "mcq": {
      "question": "Where should meaningful identifiers be used?",
      "correct": "Variables, arrays and subprograms",
      "wrong": [
        "Only variables and constants",
        "Only comments and loops",
        "Only procedures and functions"
      ]
    }
  },
  {
    "topicName": "Maintainable Programs",
    "mcq": {
      "question": "What are comments used for?",
      "correct": "To explain sections of code",
      "wrong": [
        "To store values in memory",
        "To control program flow",
        "To run code more quickly"
      ]
    }
  },
  {
    "topicName": "Maintainable Programs",
    "mcq": {
      "question": "When should comments be used?",
      "correct": "For complex or unclear code",
      "wrong": [
        "For every line of code",
        "Only for input statements",
        "Only at the program end"
      ]
    }
  },
  {
    "topicName": "Maintainable Programs",
    "mcq": {
      "question": "When should comments NOT be used?",
      "correct": "For obvious code",
      "wrong": [
        "For complex logic",
        "At the start of routines",
        "To explain algorithms"
      ]
    }
  },
  {
    "topicName": "Maintainable Programs",
    "mcq": {
      "question": "What is indentation used for?",
      "correct": "To show code structure",
      "wrong": [
        "To store program data",
        "To replace comments",
        "To speed up loops"
      ]
    }
  },
  {
    "topicName": "Maintainable Programs",
    "mcq": {
      "question": "Why is indentation important?",
      "correct": "It improves readability",
      "wrong": [
        "It reduces memory use",
        "It replaces variables",
        "It prevents all errors"
      ]
    }
  },
  {
    "topicName": "Maintainable Programs",
    "mcq": {
      "question": "What is modular programming?",
      "correct": "Splitting code into subprograms",
      "wrong": [
        "Writing code in one block",
        "Removing all comments",
        "Using only variables"
      ]
    }
  },
  {
    "topicName": "Maintainable Programs",
    "mcq": {
      "question": "Why is modular programming useful?",
      "correct": "It helps testing and reuse",
      "wrong": [
        "It removes all variables",
        "It avoids all syntax errors",
        "It replaces all loops"
      ]
    }
  },
  {
    "topicName": "Maintainable Programs",
    "mcq": {
      "question": "Why should hard-coded values be avoided?",
      "correct": "They are harder to change",
      "wrong": [
        "They improve readability",
        "They reduce program errors",
        "They make code run faster"
      ]
    }
  },
  {
    "topicName": "Maintainable Programs",
    "mcq": {
      "question": "What should be used instead of hard-coded values?",
      "correct": "Variables or constants",
      "wrong": [
        "Comments or indentation",
        "Loops or selection",
        "Functions only"
      ]
    }
  }
]
