[
  {
    "topicName": "validationbasics",
    "mcq": {
      "question": "What is validation?",
      "correct": "Checking that data is sensible and follows rules",
      "wrong": [
        "Checking that data has been entered correctly",
        "Encrypting data before it is stored",
        "Making a backup copy of data"
      ]
    }
  },
  {
    "topicName": "validationbasics",
    "mcq": {
      "question": "What is verification?",
      "correct": "Checking that data has been entered correctly",
      "wrong": [
        "Checking that data is sensible",
        "Checking that data is within a range",
        "Checking that data is encrypted"
      ]
    }
  },
  {
    "topicName": "validationbasics",
    "mcq": {
      "question": "What is the main purpose of validation?",
      "correct": "To stop unreasonable or invalid data being accepted",
      "wrong": [
        "To guarantee that the data is correct",
        "To make sure the data is backed up",
        "To hide the data from unauthorised users"
      ]
    }
  },
  {
    "topicName": "validationbasics",
    "mcq": {
      "question": "What is the main purpose of verification?",
      "correct": "To reduce errors when data is entered",
      "wrong": [
        "To check data is within allowed limits",
        "To stop users leaving fields blank",
        "To make data smaller to store"
      ]
    }
  },
  {
    "topicName": "validationbasics",
    "mcq": {
      "question": "Does validation guarantee that data is correct?",
      "correct": "No, it only checks that the data follows rules",
      "wrong": [
        "Yes, validation proves the data is correct",
        "Yes, but only for numbers",
        "No, because validation is the same as verification"
      ]
    }
  },
  {
    "topicName": "validationbasics",
    "mcq": {
      "question": "Does verification guarantee that data is correct?",
      "correct": "No, it only checks that the data was entered correctly",
      "wrong": [
        "Yes, verification proves the data is correct",
        "Yes, but only if double entry is used",
        "No, because verification checks whether data is sensible"
      ]
    }
  },
  {
    "topicName": "validationbasics",
    "mcq": {
      "question": "A user enters their age as 25 instead of 35. The data is accepted because it is a sensible number. What does this show?",
      "correct": "Validation can pass even when the data is wrong",
      "wrong": [
        "Verification always fails for ages",
        "The age must have failed a type check",
        "Validation guarantees the data is correct"
      ]
    }
  },
  {
    "topicName": "validationbasics",
    "mcq": {
      "question": "A phone number is entered twice and both entries match, but the original number should have been different. What does this show?",
      "correct": "Verification can pass even when the data is wrong",
      "wrong": [
        "Validation has failed",
        "Verification checks if data is sensible",
        "Double entry always guarantees correctness"
      ]
    }
  }
]
